flask_env.py
Flask_Env-1.1.0.dist-info/METADATA
Flask_Env-1.1.0.dist-info/RECORD
Flask_Env-1.1.0.dist-info/WHEEL
Flask_Env-1.1.0.dist-info/top_level.txt
